{
  "AD": "Anuradhapura",
  "APR": "Ampara",
  "BC": "Batticaloa",
  "BD": "Badulla",
  "CO": "Colombo",
  "GQ": "Gampaha",
  "GL": "Galle",
  "HB": "Hambantota",
  "JA": "Jaffna",
  "KE": "Kegalle",
  "KG": "Kurunegala",
  "KT": "Kalutara",
  "KY": "Kandy",
  "MB": "Mannar",
  "MH": "Matara",
  "MJ": "Monaragala",
  "MP": "Mullaitivu",
  "MT": "Matale",
  "NW": "Nuwaraeliya",
  "PR": "Polonnaruwa",
  "PX": "Puttalam",
  "RN": "Ratnapura",
  "TC": "Trincomalee",
  "VA": "Vavuniya",
  "KI": "Kilinochchi"
}
